mcemtools/__init__.py
mcemtools/analysis.py
mcemtools/cli.py
mcemtools/data.py
mcemtools/masking.py
mcemtools/mcemtools.py
mcemtools/tensor_svd.py
mcemtools/transforms.py
mcemtools/classifier/ResNet.py
mcemtools/classifier/__init__.py
mcemtools/classifier/capsnet.py
mcemtools/classifier/transregress.py
mcemtools/classifier/unet_caps.py
mcemtools/denoise/DATOS.py
mcemtools/denoise/LossFunc.py
mcemtools/denoise/__init__.py
mcemtools/denoise/cluster4_unet.py
mcemtools/denoise/denoise4_tk_r_em.py
mcemtools/denoise/denoise4_tsvd.py
mcemtools/denoise/denoise4_unet.py
mcemtools/denoise/networks.py
mcemtools-0.9.15.dist-info/licenses/AUTHORS.rst
mcemtools-0.9.15.dist-info/licenses/LICENSE
mcemtools-0.9.15.dist-info/METADATA
mcemtools-0.9.15.dist-info/WHEEL
mcemtools-0.9.15.dist-info/entry_points.txt
mcemtools-0.9.15.dist-info/top_level.txt
mcemtools-0.9.15.dist-info/RECORD
